setup.py
tornalet.py
tornalet_info.py
tornalet.egg-info/PKG-INFO
tornalet.egg-info/SOURCES.txt
tornalet.egg-info/dependency_links.txt
tornalet.egg-info/requires.txt
tornalet.egg-info/top_level.txt