Metadata-Version: 1.1
Name: tornalet
Version: 1.0.2
Summary: Tornado + Greenlet = Beautiful
Home-page: https://github.com/Gawen/tornalet
Author: Gawen Arab, Wes Mason
Author-email: g@wenarab.com
License: Apache License, Version 2.0
Platform: UNKNOWN
Classifier: Development Status :: 5 - Production/Stable
Classifier: License :: OSI Approved :: Apache Software License
Classifier: Operating System :: OS Independent
Classifier: Programming Language :: Python
Classifier: Topic :: Internet :: WWW/HTTP :: HTTP Servers
Classifier: Topic :: Software Development :: Libraries :: Python Modules
